{
  "version": "https://jsonfeed.org/version/1",
  "title": "NotAShelf/nyx",
  "home_page_url": "https://nyx.notashelf.dev",
  "feed_url": "https://nyx.notashelf.dev/feed.json",
  "items": [
    {
      "id": "0",
      "url": "https://nyx.notashelf.dev/posts/2023-01-22-system-backlight.html",
      "title": "System Backlight"
    },
    {
      "id": "1",
      "url": "https://nyx.notashelf.dev/posts/2023-03-14-impermanence.html",
      "title": "Impermanence"
    },
    {
      "id": "2",
      "url": "https://nyx.notashelf.dev/posts/2023-05-21-packaging-nextjs-webapps.html",
      "title": "Packaging Nextjs Webapps"
    },
    {
      "id": "3",
      "url": "https://nyx.notashelf.dev/posts/2023-06-07-extended-nixpkgs.html",
      "title": "Extended Nixpkgs"
    },
    {
      "id": "4",
      "url": "https://nyx.notashelf.dev/posts/2023-07-14-openssh-custom-port.html",
      "title": "Openssh Custom Port"
    },
    {
      "id": "5",
      "url": "https://nyx.notashelf.dev/posts/2023-11-11-using-headscale.html",
      "title": "Using Headscale"
    }
  ]
}
